basic_web_scraper/BasicSpider.py
basic_web_scraper/__init__.py
basic_web_scraper/custom_exceptions.py
basic_web_scraper-0.13.7.dist-info/LICENSE
basic_web_scraper-0.13.7.dist-info/METADATA
basic_web_scraper-0.13.7.dist-info/WHEEL
basic_web_scraper-0.13.7.dist-info/top_level.txt
basic_web_scraper-0.13.7.dist-info/RECORD
