Metadata-Version: 2.1
Name: basic-web-scraper
Version: 0.13.7
Summary: Basic Web Scraper made with selenium and bs4
Home-page: https://github.com/aziznal/basic-web-scraper
Author: aziznal
Author-email: aziznal.dev@gmail.com
License: MIT
Keywords: webscraper scraper spider
Platform: UNKNOWN
Classifier: Development Status :: 3 - Alpha
Classifier: Intended Audience :: Developers
Classifier: License :: OSI Approved :: MIT License
Classifier: Programming Language :: Python :: 3.7
Classifier: Operating System :: Microsoft :: Windows
Classifier: Operating System :: Unix
Classifier: Topic :: Text Processing :: Markup :: HTML
Classifier: Topic :: Scientific/Engineering :: Information Analysis
Requires-Python: >=3.7
Requires-Dist: selenium
Requires-Dist: bs4
Requires-Dist: lxml
